taskiq_sqs/__init__.py
taskiq_sqs/aws.py
taskiq_sqs/broker.py
taskiq_sqs-0.0.11.dist-info/LICENSE
taskiq_sqs-0.0.11.dist-info/METADATA
taskiq_sqs-0.0.11.dist-info/WHEEL
taskiq_sqs-0.0.11.dist-info/top_level.txt
taskiq_sqs-0.0.11.dist-info/RECORD
