Metadata-Version: 2.1
Name: taskiq-sqs
Version: 0.0.11
Summary: SQS Broker for TaskIQ
License: Apache License
Project-URL: source, https://github.com/ApeWorx/taskiq-sqs
Keywords: taskiq,broker,aws,sqs
Classifier: Development Status :: 3 - Alpha
Classifier: Intended Audience :: Developers
Classifier: Intended Audience :: End Users/Desktop
Classifier: License :: OSI Approved :: MIT License
Classifier: Natural Language :: English
Classifier: Operating System :: MacOS
Classifier: Operating System :: POSIX
Classifier: Programming Language :: Python :: 3
Classifier: Programming Language :: Python :: 3.8
Classifier: Programming Language :: Python :: 3.9
Classifier: Programming Language :: Python :: 3.10
Classifier: Programming Language :: Python :: 3.11
Requires-Python: >=3.10
License-File: LICENSE
Requires-Dist: asyncer~=0.0.5
Requires-Dist: boto3~=1.34.34
Provides-Extra: dev
Requires-Dist: black~=23.12.1; extra == "dev"
Requires-Dist: boto3-stubs[essential]~=1.34.84; extra == "dev"
Requires-Dist: build~=1.0.3; extra == "dev"
Requires-Dist: flake8~=7.0.0; extra == "dev"
Requires-Dist: isort~=5.13.2; extra == "dev"
Requires-Dist: mypy~=1.8.0; extra == "dev"
Requires-Dist: mypy-boto3-sqs~=1.34.101; extra == "dev"
Requires-Dist: pytest~=7.4.4; extra == "dev"
Requires-Dist: requests~=2.31.0; extra == "dev"
Requires-Dist: setuptools-scm~=8.0.4; extra == "dev"
Requires-Dist: taskiq<1,>=0.10.3; extra == "dev"
Requires-Dist: types-requests>=2.31.0.20240106; extra == "dev"
